rip_oppy/__init__.py
rip_oppy/__main__.py
rip_oppy/command_line.py
rip_oppy/horizons.py
rip_oppy/query.py
rip_oppy-1.0.1.dist-info/METADATA
rip_oppy-1.0.1.dist-info/WHEEL
rip_oppy-1.0.1.dist-info/entry_points.txt
rip_oppy-1.0.1.dist-info/top_level.txt
rip_oppy-1.0.1.dist-info/RECORD
