Metadata-Version: 2.1
Name: rip-oppy
Version: 1.0.1
Summary: Homage to the Mars Rover Opportunity
Home-page: https://github.com/CoraDeFrancesco/hacklahoma_2022
Author: Cora, Cosme, and Alex
Author-email: coraanndefran@gmail.com
License: MIT
Platform: UNKNOWN
Classifier: License :: OSI Approved :: MIT License
Classifier: Programming Language :: Python :: 3
Classifier: Programming Language :: Python :: 3.7
Requires-Dist: reverse-geocode
Requires-Dist: numpy
